r7kit/__init__.py
r7kit/activities.py
r7kit/base_task_workflow.py
r7kit/base_workflow.py
r7kit/child.py
r7kit/config.py
r7kit/context.py
r7kit/decorators.py
r7kit/exceptions.py
r7kit/logging.py
r7kit/models.py
r7kit/redis_client.py
r7kit/serializer.py
r7kit/stateful_workflow.py
r7kit/tasks.py
r7kit/temporal_client.py
r7kit/worker.py
r7kit/workflow_utils.py
r7kit-0.3.4.dist-info/METADATA
r7kit-0.3.4.dist-info/WHEEL
r7kit-0.3.4.dist-info/top_level.txt
r7kit-0.3.4.dist-info/RECORD
