Metadata-Version: 2.4
Name: r7kit
Version: 0.3.4
Summary: Task/workflow toolkit for Temporal + Redis
Author: Dmitry Lugin
Author-email: Your Name <you@example.com>
License: MIT
Requires-Python: >=3.10
Requires-Dist: temporalio>=1.0.0
Requires-Dist: redis>=4.6.0
Requires-Dist: pydantic>=2.0.0
Requires-Dist: orjson>=3.9.0
Requires-Dist: tomli>=2.0
Requires-Dist: tenacity
Dynamic: author
Dynamic: requires-python
